[
  {
    "tool": "web_search",
    "status": "healthy",
    "problems": [
      "Tool availability check passed",
      "Brave API key found",
      "Simulated test query executed"
    ],
    "fixAvailable": false,
    "fixSteps": [],
    "timestamp": "2026-02-06T10:42:21.851Z"
  },
  {
    "tool": "exec",
    "status": "healthy",
    "problems": [
      "Basic exec command works"
    ],
    "fixAvailable": false,
    "fixSteps": [],
    "timestamp": "2026-02-06T10:42:21.852Z"
  },
  {
    "tool": "web_fetch",
    "status": "healthy",
    "problems": [],
    "fixAvailable": false,
    "fixSteps": [],
    "timestamp": "2026-02-06T10:42:21.856Z"
  }
]